{"version": 0.6, "generator": "Overpass API 0.7.62.10 2d4cfc48", "osm3s": {"timestamp_osm_base": "2026-02-25T10:32:04Z", "copyright": "The data included in this document is from www.openstreetmap.org. The data is made available under ODbL."}, "elements": [{"type": "node", "id": 11772407498, "lat": 13.0941609, "lon": 80.2821139}, {"type": "node", "id": 11772407499, "lat": 13.0941177, "lon": 80.2823307}, {"type": "node", "id": 11772407500, "lat": 13.0939423, "lon": 80.2823549}, {"type": "node", "id": 11772407501, "lat": 13.0939721, "lon": 80.2820591}, {"type": "node", "id": 11774804744, "lat": 13.0939615, "lon": 80.2823523}, {"type": "way", "id": 1267555310, "nodes": [11772407498, 11772407499, 11774804744, 11772407500, 11772407501, 11772407498], "tags": {"leisure": "park"}}]}